ec2_ssh.py
ec2_ssh-1.9.0.dist-info/DESCRIPTION.rst
ec2_ssh-1.9.0.dist-info/METADATA
ec2_ssh-1.9.0.dist-info/RECORD
ec2_ssh-1.9.0.dist-info/WHEEL
ec2_ssh-1.9.0.dist-info/entry_points.txt
ec2_ssh-1.9.0.dist-info/metadata.json
ec2_ssh-1.9.0.dist-info/top_level.txt
