Metadata-Version: 2.0
Name: ec2-ssh
Version: 1.9.0
Summary: SSH into EC2 instances via tag name
Home-page: https://github.com/YPlan/ec2-ssh
Author: Adam Johnson
Author-email: me@adamj.eu
License: MIT
Keywords: amazon,aws,ec2,ami,ssh,cloud,boto
Platform: UNKNOWN
Classifier: Development Status :: 5 - Production/Stable
Classifier: Environment :: Console
Classifier: Environment :: Web Environment
Classifier: Intended Audience :: Developers
Classifier: License :: OSI Approved :: MIT License
Classifier: Natural Language :: English
Classifier: Operating System :: OS Independent
Classifier: Programming Language :: Python
Classifier: Programming Language :: Python :: 2
Classifier: Programming Language :: Python :: 2.7
Classifier: Programming Language :: Python :: 3
Classifier: Programming Language :: Python :: 3.5
Classifier: Topic :: Utilities
Requires-Dist: boto3 (>=1.1.0)
